[ {
  "buildOrder" : 37,
  "reportUrl" : "https://apetrovskiy.github.io/neon-compatibility/37/",
  "reportName" : "Allure Report with history",
  "data" : {
    "failed" : 6,
    "broken" : 8,
    "skipped" : 3,
    "passed" : 8,
    "unknown" : 0,
    "total" : 25
  }
}, {
  "buildOrder" : 36,
  "reportUrl" : "https://apetrovskiy.github.io/neon-compatibility/36/",
  "reportName" : "Allure Report with history",
  "data" : {
    "failed" : 6,
    "broken" : 8,
    "skipped" : 3,
    "passed" : 8,
    "unknown" : 0,
    "total" : 25
  }
}, {
  "buildOrder" : 35,
  "reportUrl" : "https://apetrovskiy.github.io/neon-compatibility/35/",
  "reportName" : "Allure Report with history",
  "data" : {
    "failed" : 6,
    "broken" : 8,
    "skipped" : 3,
    "passed" : 8,
    "unknown" : 0,
    "total" : 25
  }
}, {
  "buildOrder" : 34,
  "reportUrl" : "https://apetrovskiy.github.io/neon-compatibility/34/",
  "reportName" : "Allure Report with history",
  "data" : {
    "failed" : 78,
    "broken" : 61,
    "skipped" : 90,
    "passed" : 942,
    "unknown" : 0,
    "total" : 1171
  }
}, {
  "buildOrder" : 9,
  "reportUrl" : "https://apetrovskiy.github.io/neon-compatibility/9/",
  "reportName" : "Allure Report with history",
  "data" : {
    "failed" : 71,
    "broken" : 19,
    "skipped" : 23,
    "passed" : 252,
    "unknown" : 0,
    "total" : 365
  }
}, {
  "buildOrder" : 10,
  "reportUrl" : "https://apetrovskiy.github.io/neon-compatibility/10/",
  "reportName" : "Allure Report with history",
  "data" : {
    "failed" : 62,
    "broken" : 102,
    "skipped" : 124,
    "passed" : 476,
    "unknown" : 0,
    "total" : 764
  }
}, {
  "buildOrder" : 33,
  "reportUrl" : "https://apetrovskiy.github.io/neon-compatibility/33/",
  "reportName" : "Allure Report with history",
  "data" : {
    "failed" : 6,
    "broken" : 8,
    "skipped" : 3,
    "passed" : 8,
    "unknown" : 0,
    "total" : 25
  }
}, {
  "buildOrder" : 8,
  "reportUrl" : "https://apetrovskiy.github.io/neon-compatibility/8/",
  "reportName" : "Allure Report with history",
  "data" : {
    "failed" : 6,
    "broken" : 8,
    "skipped" : 3,
    "passed" : 8,
    "unknown" : 0,
    "total" : 25
  }
}, {
  "buildOrder" : 32,
  "reportUrl" : "https://apetrovskiy.github.io/neon-compatibility/32/",
  "reportName" : "Allure Report with history",
  "data" : {
    "failed" : 47,
    "broken" : 24,
    "skipped" : 42,
    "passed" : 1145,
    "unknown" : 0,
    "total" : 1258
  }
}, {
  "buildOrder" : 31,
  "reportUrl" : "https://apetrovskiy.github.io/neon-compatibility/31/",
  "reportName" : "Allure Report with history",
  "data" : {
    "failed" : 0,
    "broken" : 8,
    "skipped" : 0,
    "passed" : 12,
    "unknown" : 0,
    "total" : 20
  }
}, {
  "buildOrder" : 30,
  "reportUrl" : "https://apetrovskiy.github.io/neon-compatibility/30/",
  "reportName" : "Allure Report with history",
  "data" : {
    "failed" : 15,
    "broken" : 68,
    "skipped" : 75,
    "passed" : 7,
    "unknown" : 0,
    "total" : 165
  }
}, {
  "buildOrder" : 29,
  "reportUrl" : "https://apetrovskiy.github.io/neon-compatibility/29/",
  "reportName" : "Allure Report with history",
  "data" : {
    "failed" : 8,
    "broken" : 73,
    "skipped" : 106,
    "passed" : 8,
    "unknown" : 0,
    "total" : 195
  }
}, {
  "buildOrder" : 28,
  "reportUrl" : "https://apetrovskiy.github.io/neon-compatibility/28/",
  "reportName" : "Allure Report with history",
  "data" : {
    "failed" : 8,
    "broken" : 79,
    "skipped" : 66,
    "passed" : 8,
    "unknown" : 0,
    "total" : 161
  }
}, {
  "buildOrder" : 27,
  "reportUrl" : "https://apetrovskiy.github.io/neon-compatibility/27/",
  "reportName" : "Allure Report with history",
  "data" : {
    "failed" : 15,
    "broken" : 95,
    "skipped" : 107,
    "passed" : 8,
    "unknown" : 0,
    "total" : 225
  }
}, {
  "buildOrder" : 26,
  "reportUrl" : "https://apetrovskiy.github.io/neon-compatibility/26/",
  "reportName" : "Allure Report with history",
  "data" : {
    "failed" : 9,
    "broken" : 87,
    "skipped" : 59,
    "passed" : 8,
    "unknown" : 0,
    "total" : 163
  }
}, {
  "buildOrder" : 25,
  "reportUrl" : "https://apetrovskiy.github.io/neon-compatibility/25/",
  "reportName" : "Allure Report with history",
  "data" : {
    "failed" : 15,
    "broken" : 94,
    "skipped" : 107,
    "passed" : 8,
    "unknown" : 0,
    "total" : 224
  }
}, {
  "buildOrder" : 7,
  "reportUrl" : "https://apetrovskiy.github.io/neon-compatibility/7/",
  "reportName" : "Allure Report with history",
  "data" : {
    "failed" : 15,
    "broken" : 96,
    "skipped" : 107,
    "passed" : 8,
    "unknown" : 0,
    "total" : 226
  }
}, {
  "buildOrder" : 24,
  "reportUrl" : "https://apetrovskiy.github.io/neon-compatibility/24/",
  "reportName" : "Allure Report with history",
  "data" : {
    "failed" : 15,
    "broken" : 96,
    "skipped" : 107,
    "passed" : 8,
    "unknown" : 0,
    "total" : 226
  }
}, {
  "buildOrder" : 6,
  "reportUrl" : "https://apetrovskiy.github.io/neon-compatibility/6/",
  "reportName" : "Allure Report with history",
  "data" : {
    "failed" : 15,
    "broken" : 96,
    "skipped" : 107,
    "passed" : 8,
    "unknown" : 0,
    "total" : 226
  }
}, {
  "buildOrder" : 5,
  "reportUrl" : "https://apetrovskiy.github.io/neon-compatibility/5/",
  "reportName" : "Allure Report with history",
  "data" : {
    "failed" : 25,
    "broken" : 81,
    "skipped" : 99,
    "passed" : 155,
    "unknown" : 0,
    "total" : 360
  }
} ]